{"v":"5.12.1","fr":60,"ip":0,"op":76,"w":1024,"h":1024,"nm":"emoji_u1f6a6","ddd":0,"assets":[],"layers":[{"ddd":0,"ind":1,"ty":4,"nm":"mask","td":1,"sr":1,"ks":{"o":{"a":0,"k":100,"ix":11},"r":{"a":0,"k":0,"ix":10},"p":{"a":0,"k":[512.04,512,0],"ix":2,"l":2},"a":{"a":0,"k":[228.93,480.25,0],"ix":1,"l":2},"s":{"a":0,"k":[100,100,100],"ix":6,"l":2}},"ao":0,"shapes":[{"ty":"gr","it":[{"ind":0,"ty":"sh","ix":1,"ks":{"a":0,"k":{"i":[[42.16,0],[0,0],[0,42.08],[0,0],[-42.08,0],[0,0],[0,-42.08],[0,0]],"o":[[0,0],[-42.08,0],[0,0],[0,-42.08],[0,0],[42.08,0],[0,0],[-0.08,42.08]],"v":[[152.36,480],[-152.44,480],[-228.68,403.76],[-228.68,-403.76],[-152.44,-480],[152.44,-480],[228.68,-403.76],[228.68,403.76]],"c":true},"ix":2},"nm":"Path 1","mn":"ADBE Vector Shape - Group","hd":false},{"ty":"fl","c":{"a":0,"k":[0.258999992819,0.258999992819,0.258999992819,1],"ix":4},"o":{"a":0,"k":100,"ix":5},"r":1,"bm":0,"nm":"Fill 1","mn":"ADBE Vector Graphic - Fill","hd":false},{"ty":"tr","p":{"a":0,"k":[228.93,480.25],"ix":2},"a":{"a":0,"k":[0,0],"ix":1},"s":{"a":0,"k":[100,100],"ix":3},"r":{"a":0,"k":0,"ix":6},"o":{"a":0,"k":100,"ix":7},"sk":{"a":0,"k":0,"ix":4},"sa":{"a":0,"k":0,"ix":5},"nm":"Transform"}],"nm":"Group 10","np":2,"cix":2,"bm":0,"ix":1,"mn":"ADBE Vector Group","hd":false}],"ip":10,"op":26,"st":12,"ct":1,"bm":0},{"ddd":0,"ind":2,"ty":4,"nm":"red light","tt":1,"tp":1,"sr":1,"ks":{"o":{"a":1,"k":[{"i":{"x":[0.667],"y":[1]},"o":{"x":[0.333],"y":[0]},"t":10,"s":[10]},{"i":{"x":[0.667],"y":[1]},"o":{"x":[0.333],"y":[0]},"t":16,"s":[100]},{"i":{"x":[0.667],"y":[1]},"o":{"x":[0.333],"y":[0]},"t":22,"s":[100]},{"t":26,"s":[10]}],"ix":11},"r":{"a":0,"k":0,"ix":10},"p":{"a":0,"k":[534.068,512,0],"ix":2,"l":2},"a":{"a":0,"k":[301.182,480.25,0],"ix":1,"l":2},"s":{"a":0,"k":[100,100,100],"ix":6,"l":2}},"ao":0,"shapes":[{"ty":"gr","it":[{"ind":0,"ty":"sh","ix":1,"ks":{"a":0,"k":{"i":[[9.12,-17.76],[-1.04,11.2],[-12.72,13.12],[-37.04,-0.08],[-25.36,-26.48],[-0.08,-20.4],[3.68,7.2],[78.88,0]],"o":[[-3.76,7.36],[2.56,-27.28],[25.28,-26.56],[37.04,-0.16],[12.72,13.12],[0,8.88],[-9.2,-17.92],[-78.88,0]],"v":[[-115.72,49.88],[-129.8,45.72],[-99,-16.12],[0.44,-57.72],[99.96,-16.2],[130.84,46.6],[117.08,50.68],[0.52,-25.72]],"c":true},"ix":2},"nm":"Path 1","mn":"ADBE Vector Shape - Group","hd":false},{"ty":"fl","c":{"a":0,"k":[0.458999992819,0.458999992819,0.458999992819,1],"ix":4},"o":{"a":0,"k":100,"ix":5},"r":1,"bm":0,"nm":"Fill 1","mn":"ADBE Vector Graphic - Fill","hd":false},{"ty":"tr","p":{"a":0,"k":[278.674,397.33],"ix":2},"a":{"a":0,"k":[0,0],"ix":1},"s":{"a":0,"k":[100,100],"ix":3},"r":{"a":0,"k":0,"ix":6},"o":{"a":0,"k":100,"ix":7},"sk":{"a":0,"k":0,"ix":4},"sa":{"a":0,"k":0,"ix":5},"nm":"Transform"}],"nm":"Group 1","np":2,"cix":2,"bm":0,"ix":1,"mn":"ADBE Vector Group","hd":false},{"ty":"gr","it":[{"ind":0,"ty":"sh","ix":1,"ks":{"a":0,"k":{"i":[[9.12,-17.68],[-1.04,11.2],[-12.72,13.12],[-37.04,-0.08],[-25.36,-26.48],[-0.08,-20.4],[3.68,7.2],[78.88,0]],"o":[[-3.76,7.36],[2.56,-27.28],[25.28,-26.56],[37.04,-0.16],[12.72,13.12],[0,8.881],[-9.2,-17.92],[-79.04,0]],"v":[[-115.72,49.88],[-129.8,45.72],[-99,-16.12],[0.44,-57.72],[99.96,-16.2],[130.84,46.6],[117.08,50.68],[0.52,-25.72]],"c":true},"ix":2},"nm":"Path 1","mn":"ADBE Vector Shape - Group","hd":false},{"ty":"fl","c":{"a":0,"k":[0.458999992819,0.458999992819,0.458999992819,1],"ix":4},"o":{"a":0,"k":100,"ix":5},"r":1,"bm":0,"nm":"Fill 1","mn":"ADBE Vector Graphic - Fill","hd":false},{"ty":"tr","p":{"a":0,"k":[278.674,691.33],"ix":2},"a":{"a":0,"k":[0,0],"ix":1},"s":{"a":0,"k":[100,100],"ix":3},"r":{"a":0,"k":0,"ix":6},"o":{"a":0,"k":100,"ix":7},"sk":{"a":0,"k":0,"ix":4},"sa":{"a":0,"k":0,"ix":5},"nm":"Transform"}],"nm":"Group 2","np":2,"cix":2,"bm":0,"ix":2,"mn":"ADBE Vector Group","hd":false},{"ty":"gr","it":[{"ind":0,"ty":"sh","ix":1,"ks":{"a":0,"k":{"i":[[9.12,-17.76],[-1.04,11.2],[-12.72,13.12],[-37.04,-0.08],[-25.36,-26.48],[-0.08,-20.4],[3.68,7.2],[78.88,0]],"o":[[-3.76,7.36],[2.56,-27.28],[25.28,-26.56],[37.04,-0.16],[12.72,13.12],[0,8.88],[-9.2,-17.92],[-79.04,0]],"v":[[-115.72,49.88],[-129.8,45.72],[-99,-16.12],[0.44,-57.72],[99.96,-16.2],[130.84,46.6],[117.08,50.68],[0.52,-25.72]],"c":true},"ix":2},"nm":"Path 1","mn":"ADBE Vector Shape - Group","hd":false},{"ty":"fl","c":{"a":0,"k":[0.579999976065,0.416000007181,0.40800000359,1],"ix":4},"o":{"a":0,"k":100,"ix":5},"r":1,"bm":0,"nm":"Fill 1","mn":"ADBE Vector Graphic - Fill","hd":false},{"ty":"tr","p":{"a":0,"k":[278.674,103.33],"ix":2},"a":{"a":0,"k":[0,0],"ix":1},"s":{"a":0,"k":[100,100],"ix":3},"r":{"a":0,"k":0,"ix":6},"o":{"a":0,"k":100,"ix":7},"sk":{"a":0,"k":0,"ix":4},"sa":{"a":0,"k":0,"ix":5},"nm":"Transform"}],"nm":"Group 3","np":2,"cix":2,"bm":0,"ix":3,"mn":"ADBE Vector Group","hd":false},{"ty":"gr","it":[{"ind":0,"ty":"sh","ix":1,"ks":{"a":0,"k":{"i":[[14.48,4.56],[-21.36,25.68],[-4.88,-20.4],[27.52,-23.04]],"o":[[-9.12,-2.88],[31.84,-38.32],[6.8,28.56],[-17.2,14.4]],"v":[[-43.76,47.16],[-34,-13.4],[48.56,-30.36],[-8.32,9.96]],"c":true},"ix":2},"nm":"Path 1","mn":"ADBE Vector Shape - Group","hd":false},{"ty":"fl","c":{"a":0,"k":[1,0.666999966491,0.54900004069,1],"ix":4},"o":{"a":0,"k":100,"ix":5},"r":1,"bm":0,"nm":"Fill 1","mn":"ADBE Vector Graphic - Fill","hd":false},{"ty":"tr","p":{"a":0,"k":[247.994,166.53],"ix":2},"a":{"a":0,"k":[0,0],"ix":1},"s":{"a":0,"k":[100,100],"ix":3},"r":{"a":0,"k":0,"ix":6},"o":{"a":0,"k":100,"ix":7},"sk":{"a":0,"k":0,"ix":4},"sa":{"a":0,"k":0,"ix":5},"nm":"Transform"}],"nm":"Group 4","np":2,"cix":2,"bm":0,"ix":4,"mn":"ADBE Vector Group","hd":false},{"ty":"gr","it":[{"ind":0,"ty":"sh","ix":1,"ks":{"a":0,"k":{"i":[[-59.249,0],[0,-59.249],[59.249,0],[0,59.249]],"o":[[59.249,0],[0,59.249],[-59.249,0],[0,-59.249]],"v":[[0,-107.28],[107.28,0],[0,107.28],[-107.28,0]],"c":true},"ix":2},"nm":"Path 1","mn":"ADBE Vector Shape - Group","hd":false},{"ty":"fl","c":{"a":0,"k":[1,0.505999995213,0.33300000359,1],"ix":4},"o":{"a":0,"k":100,"ix":5},"r":1,"bm":0,"nm":"Fill 1","mn":"ADBE Vector Graphic - Fill","hd":false},{"ty":"tr","p":{"a":0,"k":[279.114,204.25],"ix":2},"a":{"a":0,"k":[0,0],"ix":1},"s":{"a":0,"k":[100,100],"ix":3},"r":{"a":0,"k":0,"ix":6},"o":{"a":0,"k":100,"ix":7},"sk":{"a":0,"k":0,"ix":4},"sa":{"a":0,"k":0,"ix":5},"nm":"Transform"}],"nm":"Group 5","np":2,"cix":2,"bm":0,"ix":5,"mn":"ADBE Vector Group","hd":false},{"ty":"gr","it":[{"ind":0,"ty":"sh","ix":1,"ks":{"a":0,"k":{"i":[[14.48,4.56],[-21.36,25.68],[-4.88,-20.4],[27.52,-23.04]],"o":[[-9.12,-2.88],[31.84,-38.32],[6.8,28.56],[-17.2,14.4]],"v":[[-43.76,47.16],[-34,-13.4],[48.56,-30.36],[-8.32,9.96]],"c":true},"ix":2},"nm":"Path 1","mn":"ADBE Vector Shape - Group","hd":false},{"ty":"fl","c":{"a":0,"k":[1,0.961000031116,0.616000007181,1],"ix":4},"o":{"a":0,"k":100,"ix":5},"r":1,"bm":0,"nm":"Fill 1","mn":"ADBE Vector Graphic - Fill","hd":false},{"ty":"tr","p":{"a":0,"k":[247.994,460.21],"ix":2},"a":{"a":0,"k":[0,0],"ix":1},"s":{"a":0,"k":[100,100],"ix":3},"r":{"a":0,"k":0,"ix":6},"o":{"a":0,"k":100,"ix":7},"sk":{"a":0,"k":0,"ix":4},"sa":{"a":0,"k":0,"ix":5},"nm":"Transform"}],"nm":"Group 6","np":2,"cix":2,"bm":0,"ix":6,"mn":"ADBE Vector Group","hd":false},{"ty":"gr","it":[{"ind":0,"ty":"sh","ix":1,"ks":{"a":0,"k":{"i":[[-59.249,0],[0,-59.249],[59.249,0],[0,59.249]],"o":[[59.249,0],[0,59.249],[-59.249,0],[0,-59.249]],"v":[[0,-107.28],[107.28,0],[0,107.28],[-107.28,0]],"c":true},"ix":2},"nm":"Path 1","mn":"ADBE Vector Shape - Group","hd":false},{"ty":"fl","c":{"a":0,"k":[1,0.791999966491,0.156999999402,1],"ix":4},"o":{"a":0,"k":100,"ix":5},"r":1,"bm":0,"nm":"Fill 1","mn":"ADBE Vector Graphic - Fill","hd":false},{"ty":"tr","p":{"a":0,"k":[279.114,497.93],"ix":2},"a":{"a":0,"k":[0,0],"ix":1},"s":{"a":0,"k":[100,100],"ix":3},"r":{"a":0,"k":0,"ix":6},"o":{"a":0,"k":100,"ix":7},"sk":{"a":0,"k":0,"ix":4},"sa":{"a":0,"k":0,"ix":5},"nm":"Transform"}],"nm":"Group 7","np":2,"cix":2,"bm":0,"ix":7,"mn":"ADBE Vector Group","hd":false},{"ty":"gr","it":[{"ind":0,"ty":"sh","ix":1,"ks":{"a":0,"k":{"i":[[14.48,4.561],[-21.36,25.68],[-4.88,-20.4],[27.52,-23.039]],"o":[[-9.12,-2.88],[31.84,-38.32],[6.8,28.56],[-17.2,14.4]],"v":[[-43.76,47.16],[-34,-13.401],[48.56,-30.36],[-8.32,9.96]],"c":true},"ix":2},"nm":"Path 1","mn":"ADBE Vector Shape - Group","hd":false},{"ty":"fl","c":{"a":0,"k":[0.435000011968,0.847000002394,0.435000011968,1],"ix":4},"o":{"a":0,"k":100,"ix":5},"r":1,"bm":0,"nm":"Fill 1","mn":"ADBE Vector Graphic - Fill","hd":false},{"ty":"tr","p":{"a":0,"k":[247.994,753.81],"ix":2},"a":{"a":0,"k":[0,0],"ix":1},"s":{"a":0,"k":[100,100],"ix":3},"r":{"a":0,"k":0,"ix":6},"o":{"a":0,"k":100,"ix":7},"sk":{"a":0,"k":0,"ix":4},"sa":{"a":0,"k":0,"ix":5},"nm":"Transform"}],"nm":"Group 8","np":2,"cix":2,"bm":0,"ix":8,"mn":"ADBE Vector Group","hd":false},{"ty":"gr","it":[{"ind":0,"ty":"sh","ix":1,"ks":{"a":0,"k":{"i":[[-59.249,0],[0,-59.249],[59.249,0],[0,59.249]],"o":[[59.249,0],[0,59.249],[-59.249,0],[0,-59.249]],"v":[[0,-107.28],[107.28,0],[0,107.28],[-107.28,0]],"c":true},"ix":2},"nm":"Path 1","mn":"ADBE Vector Shape - Group","hd":false},{"ty":"fl","c":{"a":0,"k":[0.298000021542,0.685999971278,0.313999998803,1],"ix":4},"o":{"a":0,"k":100,"ix":5},"r":1,"bm":0,"nm":"Fill 1","mn":"ADBE Vector Graphic - Fill","hd":false},{"ty":"tr","p":{"a":0,"k":[279.114,791.61],"ix":2},"a":{"a":0,"k":[0,0],"ix":1},"s":{"a":0,"k":[100,100],"ix":3},"r":{"a":0,"k":0,"ix":6},"o":{"a":0,"k":100,"ix":7},"sk":{"a":0,"k":0,"ix":4},"sa":{"a":0,"k":0,"ix":5},"nm":"Transform"}],"nm":"Group 9","np":2,"cix":2,"bm":0,"ix":9,"mn":"ADBE Vector Group","hd":false},{"ty":"gr","it":[{"ind":0,"ty":"sh","ix":1,"ks":{"a":0,"k":{"i":[[0,-69.731],[69.731,0],[0,69.731],[-69.731,0]],"o":[[0,69.731],[-69.731,0],[0,-69.731],[69.731,0]],"v":[[126.259,0],[0,126.259],[-126.259,0],[0,-126.259]],"c":true},"ix":2},"nm":"Path 1","mn":"ADBE Vector Shape - Group","hd":false},{"ty":"fl","c":{"a":0,"k":[0.957000014361,0.263000009574,0.211999990426,1],"ix":4},"o":{"a":0,"k":100,"ix":5},"r":1,"bm":0,"nm":"Fill 1","mn":"ADBE Vector Graphic - Fill","hd":false},{"ty":"tr","p":{"a":0,"k":[280.653,202.763],"ix":2},"a":{"a":0,"k":[0,0],"ix":1},"s":{"a":0,"k":[100,100],"ix":3},"r":{"a":0,"k":0,"ix":6},"o":{"a":0,"k":100,"ix":7},"sk":{"a":0,"k":0,"ix":4},"sa":{"a":0,"k":0,"ix":5},"nm":"Transform"}],"nm":"Group 10","np":2,"cix":2,"bm":0,"ix":10,"mn":"ADBE Vector Group","hd":false},{"ty":"gr","it":[{"ind":0,"ty":"sh","ix":1,"ks":{"a":0,"k":{"i":[[-37.032,-86.668],[81.644,0],[-33.617,113.31],[-81.644,0]],"o":[[46.182,108.084],[-81.644,0],[23.222,-78.272],[81.644,0]],"v":[[128.031,-44.521],[-0.83,147.829],[-132.676,-34.557],[-0.83,-147.829]],"c":true},"ix":2},"nm":"Path 1","mn":"ADBE Vector Shape - Group","hd":false},{"ty":"fl","c":{"a":0,"k":[0.957000014361,0.263000009574,0.211999990426,1],"ix":4},"o":{"a":0,"k":100,"ix":5},"r":1,"bm":0,"nm":"Fill 1","mn":"ADBE Vector Graphic - Fill","hd":false},{"ty":"tr","p":{"a":0,"k":[281.483,202.763],"ix":2},"a":{"a":0,"k":[0,0],"ix":1},"s":{"a":0,"k":[100,100],"ix":3},"r":{"a":0,"k":0,"ix":6},"o":{"a":0,"k":43,"ix":7},"sk":{"a":0,"k":0,"ix":4},"sa":{"a":0,"k":0,"ix":5},"nm":"Transform"}],"nm":"Group 11","np":2,"cix":2,"bm":0,"ix":11,"mn":"ADBE Vector Group","hd":false},{"ty":"gr","it":[{"ind":0,"ty":"sh","ix":1,"ks":{"a":0,"k":{"i":[[0,0],[-92.98,0.782],[-147.391,-1.778],[0,0],[147.468,0],[0,0]],"o":[[108.444,15.934],[105.741,-0.888],[147.391,1.778],[0,0],[-147.469,0],[0,0]],"v":[[-241.179,205.123],[1.499,58.665],[251.226,203.899],[274.011,-180.911],[0.007,-124.601],[-279.154,-206.228]],"c":true},"ix":2},"nm":"Path 1","mn":"ADBE Vector Shape - Group","hd":false},{"ty":"fl","c":{"a":0,"k":[0.957000014361,0.263000009574,0.211999990426,1],"ix":4},"o":{"a":0,"k":100,"ix":5},"r":1,"bm":0,"nm":"Fill 1","mn":"ADBE Vector Graphic - Fill","hd":false},{"ty":"tr","p":{"a":0,"k":[279.154,292.807],"ix":2},"a":{"a":0,"k":[0,0],"ix":1},"s":{"a":0,"k":[100,100],"ix":3},"r":{"a":0,"k":0,"ix":6},"o":{"a":0,"k":28,"ix":7},"sk":{"a":0,"k":0,"ix":4},"sa":{"a":0,"k":0,"ix":5},"nm":"Transform"}],"nm":"Group 12","np":2,"cix":2,"bm":0,"ix":12,"mn":"ADBE Vector Group","hd":false},{"ty":"gr","it":[{"ind":0,"ty":"sh","ix":1,"ks":{"a":0,"k":{"i":[[42.16,0],[0,0],[0,42.08],[0,0],[-42.08,0],[0,0],[0,-42.08],[0,0]],"o":[[0,0],[-42.08,0],[0,0],[0,-42.08],[0,0],[42.08,0],[0,0],[-0.08,42.08]],"v":[[152.36,480],[-152.44,480],[-228.68,403.76],[-228.68,-403.76],[-152.44,-480],[152.44,-480],[228.68,-403.76],[228.68,403.76]],"c":true},"ix":2},"nm":"Path 1","mn":"ADBE Vector Shape - Group","hd":false},{"ty":"fl","c":{"a":0,"k":[0.258999992819,0.258999992819,0.258999992819,1],"ix":4},"o":{"a":0,"k":100,"ix":5},"r":1,"bm":0,"nm":"Fill 1","mn":"ADBE Vector Graphic - Fill","hd":false},{"ty":"tr","p":{"a":0,"k":[279.154,480.25],"ix":2},"a":{"a":0,"k":[0,0],"ix":1},"s":{"a":0,"k":[100,100],"ix":3},"r":{"a":0,"k":0,"ix":6},"o":{"a":0,"k":100,"ix":7},"sk":{"a":0,"k":0,"ix":4},"sa":{"a":0,"k":0,"ix":5},"nm":"Transform"}],"nm":"Group 13","np":2,"cix":2,"bm":0,"ix":13,"mn":"ADBE Vector Group","hd":false}],"ip":10,"op":26,"st":12,"ct":1,"bm":0},{"ddd":0,"ind":3,"ty":4,"nm":"mask 2","td":1,"sr":1,"ks":{"o":{"a":0,"k":100,"ix":11},"r":{"a":0,"k":0,"ix":10},"p":{"a":0,"k":[512.04,512,0],"ix":2,"l":2},"a":{"a":0,"k":[228.93,480.25,0],"ix":1,"l":2},"s":{"a":0,"k":[100,100,100],"ix":6,"l":2}},"ao":0,"shapes":[{"ty":"gr","it":[{"ind":0,"ty":"sh","ix":1,"ks":{"a":0,"k":{"i":[[42.16,0],[0,0],[0,42.08],[0,0],[-42.08,0],[0,0],[0,-42.08],[0,0]],"o":[[0,0],[-42.08,0],[0,0],[0,-42.08],[0,0],[42.08,0],[0,0],[-0.08,42.08]],"v":[[152.36,480],[-152.44,480],[-228.68,403.76],[-228.68,-403.76],[-152.44,-480],[152.44,-480],[228.68,-403.76],[228.68,403.76]],"c":true},"ix":2},"nm":"Path 1","mn":"ADBE Vector Shape - Group","hd":false},{"ty":"fl","c":{"a":0,"k":[0.258999992819,0.258999992819,0.258999992819,1],"ix":4},"o":{"a":0,"k":100,"ix":5},"r":1,"bm":0,"nm":"Fill 1","mn":"ADBE Vector Graphic - Fill","hd":false},{"ty":"tr","p":{"a":0,"k":[228.93,480.25],"ix":2},"a":{"a":0,"k":[0,0],"ix":1},"s":{"a":0,"k":[100,100],"ix":3},"r":{"a":0,"k":0,"ix":6},"o":{"a":0,"k":100,"ix":7},"sk":{"a":0,"k":0,"ix":4},"sa":{"a":0,"k":0,"ix":5},"nm":"Transform"}],"nm":"Group 10","np":2,"cix":2,"bm":0,"ix":1,"mn":"ADBE Vector Group","hd":false}],"ip":34,"op":50,"st":36,"ct":1,"bm":0},{"ddd":0,"ind":4,"ty":4,"nm":"yellow ligut","tt":1,"tp":3,"sr":1,"ks":{"o":{"a":1,"k":[{"i":{"x":[0.667],"y":[1]},"o":{"x":[0.333],"y":[0]},"t":34,"s":[10]},{"i":{"x":[0.667],"y":[1]},"o":{"x":[0.333],"y":[0]},"t":40,"s":[100]},{"i":{"x":[0.667],"y":[1]},"o":{"x":[0.333],"y":[0]},"t":46,"s":[100]},{"t":50,"s":[10]}],"ix":11},"r":{"a":0,"k":0,"ix":10},"p":{"a":0,"k":[534.068,512,0],"ix":2,"l":2},"a":{"a":0,"k":[301.182,480.25,0],"ix":1,"l":2},"s":{"a":0,"k":[100,100,100],"ix":6,"l":2}},"ao":0,"shapes":[{"ty":"gr","it":[{"ind":0,"ty":"sh","ix":1,"ks":{"a":0,"k":{"i":[[9.12,-17.76],[-1.04,11.2],[-12.72,13.12],[-37.04,-0.08],[-25.36,-26.48],[-0.08,-20.4],[3.68,7.2],[78.88,0]],"o":[[-3.76,7.36],[2.56,-27.28],[25.28,-26.56],[37.04,-0.16],[12.72,13.12],[0,8.88],[-9.2,-17.92],[-78.88,0]],"v":[[-115.72,49.88],[-129.8,45.72],[-99,-16.12],[0.44,-57.72],[99.96,-16.2],[130.84,46.6],[117.08,50.68],[0.52,-25.72]],"c":true},"ix":2},"nm":"Path 1","mn":"ADBE Vector Shape - Group","hd":false},{"ty":"fl","c":{"a":0,"k":[0.458999992819,0.451000019148,0.375999989229,1],"ix":4},"o":{"a":0,"k":100,"ix":5},"r":1,"bm":0,"nm":"Fill 1","mn":"ADBE Vector Graphic - Fill","hd":false},{"ty":"tr","p":{"a":0,"k":[278.674,397.33],"ix":2},"a":{"a":0,"k":[0,0],"ix":1},"s":{"a":0,"k":[100,100],"ix":3},"r":{"a":0,"k":0,"ix":6},"o":{"a":0,"k":100,"ix":7},"sk":{"a":0,"k":0,"ix":4},"sa":{"a":0,"k":0,"ix":5},"nm":"Transform"}],"nm":"Group 1","np":2,"cix":2,"bm":0,"ix":1,"mn":"ADBE Vector Group","hd":false},{"ty":"gr","it":[{"ind":0,"ty":"sh","ix":1,"ks":{"a":0,"k":{"i":[[14.48,4.56],[-21.36,25.68],[-4.88,-20.4],[27.52,-23.04]],"o":[[-9.12,-2.88],[31.84,-38.32],[6.8,28.56],[-17.2,14.4]],"v":[[-43.76,47.16],[-34,-13.4],[48.56,-30.36],[-8.32,9.96]],"c":true},"ix":2},"nm":"Path 1","mn":"ADBE Vector Shape - Group","hd":false},{"ty":"fl","c":{"a":0,"k":[1,0.984000052658,0.830999995213,1],"ix":4},"o":{"a":0,"k":100,"ix":5},"r":1,"bm":0,"nm":"Fill 1","mn":"ADBE Vector Graphic - Fill","hd":false},{"ty":"tr","p":{"a":0,"k":[247.994,460.21],"ix":2},"a":{"a":0,"k":[0,0],"ix":1},"s":{"a":0,"k":[100,100],"ix":3},"r":{"a":0,"k":0,"ix":6},"o":{"a":0,"k":100,"ix":7},"sk":{"a":0,"k":0,"ix":4},"sa":{"a":0,"k":0,"ix":5},"nm":"Transform"}],"nm":"Group 6","np":2,"cix":2,"bm":0,"ix":2,"mn":"ADBE Vector Group","hd":false},{"ty":"gr","it":[{"ind":0,"ty":"sh","ix":1,"ks":{"a":0,"k":{"i":[[-59.249,0],[0,-59.249],[59.249,0],[0,59.249]],"o":[[59.249,0],[0,59.249],[-59.249,0],[0,-59.249]],"v":[[0,-107.28],[107.28,0],[0,107.28],[-107.28,0]],"c":true},"ix":2},"nm":"Path 1","mn":"ADBE Vector Shape - Group","hd":false},{"ty":"fl","c":{"a":0,"k":[1,0.961000031116,0.616000007181,1],"ix":4},"o":{"a":0,"k":100,"ix":5},"r":1,"bm":0,"nm":"Fill 1","mn":"ADBE Vector Graphic - Fill","hd":false},{"ty":"tr","p":{"a":0,"k":[279.114,497.93],"ix":2},"a":{"a":0,"k":[0,0],"ix":1},"s":{"a":0,"k":[100,100],"ix":3},"r":{"a":0,"k":0,"ix":6},"o":{"a":0,"k":100,"ix":7},"sk":{"a":0,"k":0,"ix":4},"sa":{"a":0,"k":0,"ix":5},"nm":"Transform"}],"nm":"Group 7","np":2,"cix":2,"bm":0,"ix":3,"mn":"ADBE Vector Group","hd":false},{"ty":"gr","it":[{"ind":0,"ty":"sh","ix":1,"ks":{"a":0,"k":{"i":[[0,-69.73],[69.731,0],[0,69.731],[-69.731,0]],"o":[[0,69.731],[-69.731,0],[0,-69.73],[69.731,0]],"v":[[126.259,0],[0,126.259],[-126.259,0],[0,-126.259]],"c":true},"ix":2},"nm":"Path 1","mn":"ADBE Vector Shape - Group","hd":false},{"ty":"fl","c":{"a":0,"k":[1,0.791999966491,0.156999999402,1],"ix":4},"o":{"a":0,"k":100,"ix":5},"r":1,"bm":0,"nm":"Fill 1","mn":"ADBE Vector Graphic - Fill","hd":false},{"ty":"tr","p":{"a":0,"k":[279.331,497.876],"ix":2},"a":{"a":0,"k":[0,0],"ix":1},"s":{"a":0,"k":[100,100],"ix":3},"r":{"a":0,"k":0,"ix":6},"o":{"a":0,"k":100,"ix":7},"sk":{"a":0,"k":0,"ix":4},"sa":{"a":0,"k":0,"ix":5},"nm":"Transform"}],"nm":"Group 10","np":2,"cix":2,"bm":0,"ix":4,"mn":"ADBE Vector Group","hd":false},{"ty":"gr","it":[{"ind":0,"ty":"sh","ix":1,"ks":{"a":0,"k":{"i":[[-37.031,-86.668],[81.644,0],[-33.617,113.31],[-81.644,0]],"o":[[46.182,108.084],[-81.644,0],[23.222,-78.272],[81.644,0]],"v":[[128.031,-44.521],[-0.83,147.829],[-132.676,-34.557],[-0.83,-147.829]],"c":true},"ix":2},"nm":"Path 1","mn":"ADBE Vector Shape - Group","hd":false},{"ty":"fl","c":{"a":0,"k":[1,0.791999966491,0.156999999402,1],"ix":4},"o":{"a":0,"k":100,"ix":5},"r":1,"bm":0,"nm":"Fill 1","mn":"ADBE Vector Graphic - Fill","hd":false},{"ty":"tr","p":{"a":0,"k":[280.16,497.876],"ix":2},"a":{"a":0,"k":[0,0],"ix":1},"s":{"a":0,"k":[100,100],"ix":3},"r":{"a":0,"k":0,"ix":6},"o":{"a":0,"k":43,"ix":7},"sk":{"a":0,"k":0,"ix":4},"sa":{"a":0,"k":0,"ix":5},"nm":"Transform"}],"nm":"Group 11","np":2,"cix":2,"bm":0,"ix":5,"mn":"ADBE Vector Group","hd":false},{"ty":"gr","it":[{"ind":0,"ty":"sh","ix":1,"ks":{"a":0,"k":{"i":[[0,0],[-92.98,0.781],[-147.391,-1.778],[0,0],[147.468,0],[0,0]],"o":[[108.444,15.934],[105.741,-0.89],[147.391,1.778],[0,0],[-147.469,0],[0,0]],"v":[[-241.179,205.123],[1.499,58.666],[251.226,203.899],[274.011,-180.911],[0.007,-124.601],[-279.154,-206.228]],"c":true},"ix":2},"nm":"Path 1","mn":"ADBE Vector Shape - Group","hd":false},{"ty":"fl","c":{"a":0,"k":[1,0.791999966491,0.156999999402,1],"ix":4},"o":{"a":0,"k":100,"ix":5},"r":1,"bm":0,"nm":"Fill 1","mn":"ADBE Vector Graphic - Fill","hd":false},{"ty":"tr","p":{"a":0,"k":[279.154,590.807],"ix":2},"a":{"a":0,"k":[0,0],"ix":1},"s":{"a":0,"k":[100,100],"ix":3},"r":{"a":0,"k":0,"ix":6},"o":{"a":0,"k":28,"ix":7},"sk":{"a":0,"k":0,"ix":4},"sa":{"a":0,"k":0,"ix":5},"nm":"Transform"}],"nm":"Group 12","np":2,"cix":2,"bm":0,"ix":6,"mn":"ADBE Vector Group","hd":false}],"ip":34,"op":50,"st":36,"ct":1,"bm":0},{"ddd":0,"ind":5,"ty":4,"nm":"mask 3","td":1,"sr":1,"ks":{"o":{"a":0,"k":100,"ix":11},"r":{"a":0,"k":0,"ix":10},"p":{"a":0,"k":[512.04,512,0],"ix":2,"l":2},"a":{"a":0,"k":[228.93,480.25,0],"ix":1,"l":2},"s":{"a":0,"k":[100,100,100],"ix":6,"l":2}},"ao":0,"shapes":[{"ty":"gr","it":[{"ind":0,"ty":"sh","ix":1,"ks":{"a":0,"k":{"i":[[42.16,0],[0,0],[0,42.08],[0,0],[-42.08,0],[0,0],[0,-42.08],[0,0]],"o":[[0,0],[-42.08,0],[0,0],[0,-42.08],[0,0],[42.08,0],[0,0],[-0.08,42.08]],"v":[[152.36,480],[-152.44,480],[-228.68,403.76],[-228.68,-403.76],[-152.44,-480],[152.44,-480],[228.68,-403.76],[228.68,403.76]],"c":true},"ix":2},"nm":"Path 1","mn":"ADBE Vector Shape - Group","hd":false},{"ty":"fl","c":{"a":0,"k":[0.258999992819,0.258999992819,0.258999992819,1],"ix":4},"o":{"a":0,"k":100,"ix":5},"r":1,"bm":0,"nm":"Fill 1","mn":"ADBE Vector Graphic - Fill","hd":false},{"ty":"tr","p":{"a":0,"k":[228.93,480.25],"ix":2},"a":{"a":0,"k":[0,0],"ix":1},"s":{"a":0,"k":[100,100],"ix":3},"r":{"a":0,"k":0,"ix":6},"o":{"a":0,"k":100,"ix":7},"sk":{"a":0,"k":0,"ix":4},"sa":{"a":0,"k":0,"ix":5},"nm":"Transform"}],"nm":"Group 10","np":2,"cix":2,"bm":0,"ix":1,"mn":"ADBE Vector Group","hd":false}],"ip":58,"op":74,"st":60,"ct":1,"bm":0},{"ddd":0,"ind":6,"ty":4,"nm":"green light","tt":1,"tp":5,"sr":1,"ks":{"o":{"a":1,"k":[{"i":{"x":[0.667],"y":[1]},"o":{"x":[0.333],"y":[0]},"t":58,"s":[10]},{"i":{"x":[0.667],"y":[1]},"o":{"x":[0.333],"y":[0]},"t":64,"s":[100]},{"i":{"x":[0.667],"y":[1]},"o":{"x":[0.333],"y":[0]},"t":70,"s":[100]},{"t":74,"s":[10]}],"ix":11},"r":{"a":0,"k":0,"ix":10},"p":{"a":0,"k":[534.068,574.604,0],"ix":2,"l":2},"a":{"a":0,"k":[301.182,542.854,0],"ix":1,"l":2},"s":{"a":0,"k":[100,100,100],"ix":6,"l":2}},"ao":0,"shapes":[{"ty":"gr","it":[{"ind":0,"ty":"sh","ix":1,"ks":{"a":0,"k":{"i":[[9.12,-17.68],[-1.04,11.2],[-12.72,13.12],[-37.04,-0.08],[-25.36,-26.48],[-0.08,-20.4],[3.68,7.2],[78.88,0]],"o":[[-3.76,7.36],[2.56,-27.28],[25.28,-26.56],[37.04,-0.16],[12.72,13.12],[0,8.881],[-9.2,-17.92],[-79.04,0]],"v":[[-115.72,49.88],[-129.8,45.72],[-99,-16.12],[0.44,-57.72],[99.96,-16.2],[130.84,46.6],[117.08,50.68],[0.52,-25.72]],"c":true},"ix":2},"nm":"Path 1","mn":"ADBE Vector Shape - Group","hd":false},{"ty":"fl","c":{"a":0,"k":[0.349000010771,0.458999992819,0.322000002394,1],"ix":4},"o":{"a":0,"k":100,"ix":5},"r":1,"bm":0,"nm":"Fill 1","mn":"ADBE Vector Graphic - Fill","hd":false},{"ty":"tr","p":{"a":0,"k":[278.674,691.33],"ix":2},"a":{"a":0,"k":[0,0],"ix":1},"s":{"a":0,"k":[100,100],"ix":3},"r":{"a":0,"k":0,"ix":6},"o":{"a":0,"k":100,"ix":7},"sk":{"a":0,"k":0,"ix":4},"sa":{"a":0,"k":0,"ix":5},"nm":"Transform"}],"nm":"Group 2","np":2,"cix":2,"bm":0,"ix":1,"mn":"ADBE Vector Group","hd":false},{"ty":"gr","it":[{"ind":0,"ty":"sh","ix":1,"ks":{"a":0,"k":{"i":[[14.48,4.561],[-21.36,25.68],[-4.88,-20.4],[27.52,-23.039]],"o":[[-9.12,-2.88],[31.84,-38.32],[6.8,28.56],[-17.2,14.4]],"v":[[-43.76,47.16],[-34,-13.401],[48.56,-30.36],[-8.32,9.96]],"c":true},"ix":2},"nm":"Path 1","mn":"ADBE Vector Shape - Group","hd":false},{"ty":"fl","c":{"a":0,"k":[0.722000002394,0.847000002394,0.722000002394,1],"ix":4},"o":{"a":0,"k":100,"ix":5},"r":1,"bm":0,"nm":"Fill 1","mn":"ADBE Vector Graphic - Fill","hd":false},{"ty":"tr","p":{"a":0,"k":[247.994,753.81],"ix":2},"a":{"a":0,"k":[0,0],"ix":1},"s":{"a":0,"k":[100,100],"ix":3},"r":{"a":0,"k":0,"ix":6},"o":{"a":0,"k":100,"ix":7},"sk":{"a":0,"k":0,"ix":4},"sa":{"a":0,"k":0,"ix":5},"nm":"Transform"}],"nm":"Group 8","np":2,"cix":2,"bm":0,"ix":2,"mn":"ADBE Vector Group","hd":false},{"ty":"gr","it":[{"ind":0,"ty":"sh","ix":1,"ks":{"a":0,"k":{"i":[[-59.249,0],[0,-59.249],[59.249,0],[0,59.249]],"o":[[59.249,0],[0,59.249],[-59.249,0],[0,-59.249]],"v":[[0,-107.28],[107.28,0],[0,107.28],[-107.28,0]],"c":true},"ix":2},"nm":"Path 1","mn":"ADBE Vector Shape - Group","hd":false},{"ty":"fl","c":{"a":0,"k":[0.435000011968,0.847000002394,0.435000011968,1],"ix":4},"o":{"a":0,"k":100,"ix":5},"r":1,"bm":0,"nm":"Fill 1","mn":"ADBE Vector Graphic - Fill","hd":false},{"ty":"tr","p":{"a":0,"k":[279.114,791.61],"ix":2},"a":{"a":0,"k":[0,0],"ix":1},"s":{"a":0,"k":[100,100],"ix":3},"r":{"a":0,"k":0,"ix":6},"o":{"a":0,"k":100,"ix":7},"sk":{"a":0,"k":0,"ix":4},"sa":{"a":0,"k":0,"ix":5},"nm":"Transform"}],"nm":"Group 9","np":2,"cix":2,"bm":0,"ix":3,"mn":"ADBE Vector Group","hd":false},{"ty":"gr","it":[{"ind":0,"ty":"sh","ix":1,"ks":{"a":0,"k":{"i":[[0,-69.73],[69.731,0],[0,69.731],[-69.731,0]],"o":[[0,69.731],[-69.731,0],[0,-69.73],[69.731,0]],"v":[[126.259,0],[0,126.26],[-126.259,0],[0,-126.259]],"c":true},"ix":2},"nm":"Path 1","mn":"ADBE Vector Shape - Group","hd":false},{"ty":"fl","c":{"a":0,"k":[0.298000021542,0.685999971278,0.313999998803,1],"ix":4},"o":{"a":0,"k":100,"ix":5},"r":1,"bm":0,"nm":"Fill 1","mn":"ADBE Vector Graphic - Fill","hd":false},{"ty":"tr","p":{"a":0,"k":[279.331,790.876],"ix":2},"a":{"a":0,"k":[0,0],"ix":1},"s":{"a":0,"k":[100,100],"ix":3},"r":{"a":0,"k":0,"ix":6},"o":{"a":0,"k":100,"ix":7},"sk":{"a":0,"k":0,"ix":4},"sa":{"a":0,"k":0,"ix":5},"nm":"Transform"}],"nm":"Group 10","np":2,"cix":2,"bm":0,"ix":4,"mn":"ADBE Vector Group","hd":false},{"ty":"gr","it":[{"ind":0,"ty":"sh","ix":1,"ks":{"a":0,"k":{"i":[[-37.031,-86.668],[81.644,0],[-33.617,113.31],[-81.644,0]],"o":[[46.182,108.084],[-81.644,0],[23.222,-78.272],[81.644,0]],"v":[[128.031,-44.521],[-0.83,147.829],[-132.676,-34.557],[-0.83,-147.83]],"c":true},"ix":2},"nm":"Path 1","mn":"ADBE Vector Shape - Group","hd":false},{"ty":"fl","c":{"a":0,"k":[0.298000021542,0.685999971278,0.313999998803,1],"ix":4},"o":{"a":0,"k":100,"ix":5},"r":1,"bm":0,"nm":"Fill 1","mn":"ADBE Vector Graphic - Fill","hd":false},{"ty":"tr","p":{"a":0,"k":[280.16,790.876],"ix":2},"a":{"a":0,"k":[0,0],"ix":1},"s":{"a":0,"k":[100,100],"ix":3},"r":{"a":0,"k":0,"ix":6},"o":{"a":0,"k":43,"ix":7},"sk":{"a":0,"k":0,"ix":4},"sa":{"a":0,"k":0,"ix":5},"nm":"Transform"}],"nm":"Group 11","np":2,"cix":2,"bm":0,"ix":5,"mn":"ADBE Vector Group","hd":false},{"ty":"gr","it":[{"ind":0,"ty":"sh","ix":1,"ks":{"a":0,"k":{"i":[[0,0],[-92.98,0.781],[-147.391,-1.777],[0,0],[147.468,0],[0,0]],"o":[[108.444,15.934],[105.741,-0.889],[147.391,1.779],[0,0],[-147.469,0],[0,0]],"v":[[-241.179,267.553],[-7.002,181.519],[251.226,266.328],[274.011,-118.481],[0.007,-62.172],[-279.154,-143.798]],"c":true},"ix":2},"nm":"Path 1","mn":"ADBE Vector Shape - Group","hd":false},{"ty":"fl","c":{"a":0,"k":[0.298000021542,0.685999971278,0.313999998803,1],"ix":4},"o":{"a":0,"k":100,"ix":5},"r":1,"bm":0,"nm":"Fill 1","mn":"ADBE Vector Graphic - Fill","hd":false},{"ty":"tr","p":{"a":0,"k":[279.154,816.453],"ix":2},"a":{"a":0,"k":[0,0],"ix":1},"s":{"a":0,"k":[100,100],"ix":3},"r":{"a":0,"k":0,"ix":6},"o":{"a":0,"k":28,"ix":7},"sk":{"a":0,"k":0,"ix":4},"sa":{"a":0,"k":0,"ix":5},"nm":"Transform"}],"nm":"Group 12","np":2,"cix":2,"bm":0,"ix":6,"mn":"ADBE Vector Group","hd":false}],"ip":58,"op":74,"st":60,"ct":1,"bm":0},{"ddd":0,"ind":7,"ty":4,"nm":"53 Vertical traffic light","sr":1,"ks":{"o":{"a":0,"k":100,"ix":11},"r":{"a":0,"k":0,"ix":10},"p":{"a":0,"k":[512.04,512,0],"ix":2,"l":2},"a":{"a":0,"k":[228.93,480.25,0],"ix":1,"l":2},"s":{"a":0,"k":[100,100,100],"ix":6,"l":2}},"ao":0,"shapes":[{"ty":"gr","it":[{"ind":0,"ty":"sh","ix":1,"ks":{"a":0,"k":{"i":[[9.12,-17.76],[-1.04,11.2],[-12.72,13.12],[-37.04,-0.08],[-25.36,-26.48],[-0.08,-20.4],[3.68,7.2],[78.88,0]],"o":[[-3.76,7.36],[2.56,-27.28],[25.28,-26.56],[37.04,-0.16],[12.72,13.12],[0,8.88],[-9.2,-17.92],[-78.88,0]],"v":[[-115.72,49.88],[-129.8,45.72],[-99,-16.12],[0.44,-57.72],[99.96,-16.2],[130.84,46.6],[117.08,50.68],[0.52,-25.72]],"c":true},"ix":2},"nm":"Path 1","mn":"ADBE Vector Shape - Group","hd":false},{"ty":"fl","c":{"a":0,"k":[0.458999992819,0.458999992819,0.458999992819,1],"ix":4},"o":{"a":0,"k":100,"ix":5},"r":1,"bm":0,"nm":"Fill 1","mn":"ADBE Vector Graphic - Fill","hd":false},{"ty":"tr","p":{"a":0,"k":[228.45,397.33],"ix":2},"a":{"a":0,"k":[0,0],"ix":1},"s":{"a":0,"k":[100,100],"ix":3},"r":{"a":0,"k":0,"ix":6},"o":{"a":0,"k":100,"ix":7},"sk":{"a":0,"k":0,"ix":4},"sa":{"a":0,"k":0,"ix":5},"nm":"Transform"}],"nm":"Group 1","np":2,"cix":2,"bm":0,"ix":1,"mn":"ADBE Vector Group","hd":false},{"ty":"gr","it":[{"ind":0,"ty":"sh","ix":1,"ks":{"a":0,"k":{"i":[[9.12,-17.68],[-1.04,11.2],[-12.72,13.12],[-37.04,-0.08],[-25.36,-26.48],[-0.08,-20.4],[3.68,7.2],[78.88,0]],"o":[[-3.76,7.36],[2.56,-27.28],[25.28,-26.56],[37.04,-0.16],[12.72,13.12],[0,8.881],[-9.2,-17.92],[-79.04,0]],"v":[[-115.72,49.88],[-129.8,45.72],[-99,-16.12],[0.44,-57.72],[99.96,-16.2],[130.84,46.6],[117.08,50.68],[0.52,-25.72]],"c":true},"ix":2},"nm":"Path 1","mn":"ADBE Vector Shape - Group","hd":false},{"ty":"fl","c":{"a":0,"k":[0.458999992819,0.458999992819,0.458999992819,1],"ix":4},"o":{"a":0,"k":100,"ix":5},"r":1,"bm":0,"nm":"Fill 1","mn":"ADBE Vector Graphic - Fill","hd":false},{"ty":"tr","p":{"a":0,"k":[228.45,691.33],"ix":2},"a":{"a":0,"k":[0,0],"ix":1},"s":{"a":0,"k":[100,100],"ix":3},"r":{"a":0,"k":0,"ix":6},"o":{"a":0,"k":100,"ix":7},"sk":{"a":0,"k":0,"ix":4},"sa":{"a":0,"k":0,"ix":5},"nm":"Transform"}],"nm":"Group 2","np":2,"cix":2,"bm":0,"ix":2,"mn":"ADBE Vector Group","hd":false},{"ty":"gr","it":[{"ind":0,"ty":"sh","ix":1,"ks":{"a":0,"k":{"i":[[9.12,-17.76],[-1.04,11.2],[-12.72,13.12],[-37.04,-0.08],[-25.36,-26.48],[-0.08,-20.4],[3.68,7.2],[78.88,0]],"o":[[-3.76,7.36],[2.56,-27.28],[25.28,-26.56],[37.04,-0.16],[12.72,13.12],[0,8.88],[-9.2,-17.92],[-79.04,0]],"v":[[-115.72,49.88],[-129.8,45.72],[-99,-16.12],[0.44,-57.72],[99.96,-16.2],[130.84,46.6],[117.08,50.68],[0.52,-25.72]],"c":true},"ix":2},"nm":"Path 1","mn":"ADBE Vector Shape - Group","hd":false},{"ty":"fl","c":{"a":0,"k":[0.458999992819,0.458999992819,0.458999992819,1],"ix":4},"o":{"a":0,"k":100,"ix":5},"r":1,"bm":0,"nm":"Fill 1","mn":"ADBE Vector Graphic - Fill","hd":false},{"ty":"tr","p":{"a":0,"k":[228.45,103.33],"ix":2},"a":{"a":0,"k":[0,0],"ix":1},"s":{"a":0,"k":[100,100],"ix":3},"r":{"a":0,"k":0,"ix":6},"o":{"a":0,"k":100,"ix":7},"sk":{"a":0,"k":0,"ix":4},"sa":{"a":0,"k":0,"ix":5},"nm":"Transform"}],"nm":"Group 3","np":2,"cix":2,"bm":0,"ix":3,"mn":"ADBE Vector Group","hd":false},{"ty":"gr","it":[{"ind":0,"ty":"sh","ix":1,"ks":{"a":0,"k":{"i":[[14.48,4.56],[-21.36,25.68],[-4.88,-20.4],[27.52,-23.04]],"o":[[-9.12,-2.88],[31.84,-38.32],[6.8,28.56],[-17.2,14.4]],"v":[[-43.76,47.16],[-34,-13.4],[48.56,-30.36],[-8.32,9.96]],"c":true},"ix":2},"nm":"Path 1","mn":"ADBE Vector Shape - Group","hd":false},{"ty":"fl","c":{"a":0,"k":[1,0.505999995213,0.33300000359,1],"ix":4},"o":{"a":0,"k":100,"ix":5},"r":1,"bm":0,"nm":"Fill 1","mn":"ADBE Vector Graphic - Fill","hd":false},{"ty":"tr","p":{"a":0,"k":[197.77,166.53],"ix":2},"a":{"a":0,"k":[0,0],"ix":1},"s":{"a":0,"k":[100,100],"ix":3},"r":{"a":0,"k":0,"ix":6},"o":{"a":0,"k":100,"ix":7},"sk":{"a":0,"k":0,"ix":4},"sa":{"a":0,"k":0,"ix":5},"nm":"Transform"}],"nm":"Group 4","np":2,"cix":2,"bm":0,"ix":4,"mn":"ADBE Vector Group","hd":false},{"ty":"gr","it":[{"ind":0,"ty":"sh","ix":1,"ks":{"a":0,"k":{"i":[[-59.249,0],[0,-59.249],[59.249,0],[0,59.249]],"o":[[59.249,0],[0,59.249],[-59.249,0],[0,-59.249]],"v":[[0,-107.28],[107.28,0],[0,107.28],[-107.28,0]],"c":true},"ix":2},"nm":"Path 1","mn":"ADBE Vector Shape - Group","hd":false},{"ty":"fl","c":{"a":0,"k":[0.957000014361,0.263000009574,0.211999990426,1],"ix":4},"o":{"a":0,"k":100,"ix":5},"r":1,"bm":0,"nm":"Fill 1","mn":"ADBE Vector Graphic - Fill","hd":false},{"ty":"tr","p":{"a":0,"k":[228.89,204.25],"ix":2},"a":{"a":0,"k":[0,0],"ix":1},"s":{"a":0,"k":[100,100],"ix":3},"r":{"a":0,"k":0,"ix":6},"o":{"a":0,"k":100,"ix":7},"sk":{"a":0,"k":0,"ix":4},"sa":{"a":0,"k":0,"ix":5},"nm":"Transform"}],"nm":"Group 5","np":2,"cix":2,"bm":0,"ix":5,"mn":"ADBE Vector Group","hd":false},{"ty":"gr","it":[{"ind":0,"ty":"sh","ix":1,"ks":{"a":0,"k":{"i":[[14.48,4.56],[-21.36,25.68],[-4.88,-20.4],[27.52,-23.04]],"o":[[-9.12,-2.88],[31.84,-38.32],[6.8,28.56],[-17.2,14.4]],"v":[[-43.76,47.16],[-34,-13.4],[48.56,-30.36],[-8.32,9.96]],"c":true},"ix":2},"nm":"Path 1","mn":"ADBE Vector Shape - Group","hd":false},{"ty":"fl","c":{"a":0,"k":[1,0.961000031116,0.616000007181,1],"ix":4},"o":{"a":0,"k":100,"ix":5},"r":1,"bm":0,"nm":"Fill 1","mn":"ADBE Vector Graphic - Fill","hd":false},{"ty":"tr","p":{"a":0,"k":[197.77,460.21],"ix":2},"a":{"a":0,"k":[0,0],"ix":1},"s":{"a":0,"k":[100,100],"ix":3},"r":{"a":0,"k":0,"ix":6},"o":{"a":0,"k":100,"ix":7},"sk":{"a":0,"k":0,"ix":4},"sa":{"a":0,"k":0,"ix":5},"nm":"Transform"}],"nm":"Group 6","np":2,"cix":2,"bm":0,"ix":6,"mn":"ADBE Vector Group","hd":false},{"ty":"gr","it":[{"ind":0,"ty":"sh","ix":1,"ks":{"a":0,"k":{"i":[[-59.249,0],[0,-59.249],[59.249,0],[0,59.249]],"o":[[59.249,0],[0,59.249],[-59.249,0],[0,-59.249]],"v":[[0,-107.28],[107.28,0],[0,107.28],[-107.28,0]],"c":true},"ix":2},"nm":"Path 1","mn":"ADBE Vector Shape - Group","hd":false},{"ty":"fl","c":{"a":0,"k":[1,0.791999966491,0.156999999402,1],"ix":4},"o":{"a":0,"k":100,"ix":5},"r":1,"bm":0,"nm":"Fill 1","mn":"ADBE Vector Graphic - Fill","hd":false},{"ty":"tr","p":{"a":0,"k":[228.89,497.93],"ix":2},"a":{"a":0,"k":[0,0],"ix":1},"s":{"a":0,"k":[100,100],"ix":3},"r":{"a":0,"k":0,"ix":6},"o":{"a":0,"k":100,"ix":7},"sk":{"a":0,"k":0,"ix":4},"sa":{"a":0,"k":0,"ix":5},"nm":"Transform"}],"nm":"Group 7","np":2,"cix":2,"bm":0,"ix":7,"mn":"ADBE Vector Group","hd":false},{"ty":"gr","it":[{"ind":0,"ty":"sh","ix":1,"ks":{"a":0,"k":{"i":[[14.48,4.561],[-21.36,25.68],[-4.88,-20.4],[27.52,-23.039]],"o":[[-9.12,-2.88],[31.84,-38.32],[6.8,28.56],[-17.2,14.4]],"v":[[-43.76,47.16],[-34,-13.401],[48.56,-30.36],[-8.32,9.96]],"c":true},"ix":2},"nm":"Path 1","mn":"ADBE Vector Shape - Group","hd":false},{"ty":"fl","c":{"a":0,"k":[0.435000011968,0.847000002394,0.435000011968,1],"ix":4},"o":{"a":0,"k":100,"ix":5},"r":1,"bm":0,"nm":"Fill 1","mn":"ADBE Vector Graphic - Fill","hd":false},{"ty":"tr","p":{"a":0,"k":[197.77,753.81],"ix":2},"a":{"a":0,"k":[0,0],"ix":1},"s":{"a":0,"k":[100,100],"ix":3},"r":{"a":0,"k":0,"ix":6},"o":{"a":0,"k":100,"ix":7},"sk":{"a":0,"k":0,"ix":4},"sa":{"a":0,"k":0,"ix":5},"nm":"Transform"}],"nm":"Group 8","np":2,"cix":2,"bm":0,"ix":8,"mn":"ADBE Vector Group","hd":false},{"ty":"gr","it":[{"ind":0,"ty":"sh","ix":1,"ks":{"a":0,"k":{"i":[[-59.249,0],[0,-59.249],[59.249,0],[0,59.249]],"o":[[59.249,0],[0,59.249],[-59.249,0],[0,-59.249]],"v":[[0,-107.28],[107.28,0],[0,107.28],[-107.28,0]],"c":true},"ix":2},"nm":"Path 1","mn":"ADBE Vector Shape - Group","hd":false},{"ty":"fl","c":{"a":0,"k":[0.298000021542,0.685999971278,0.313999998803,1],"ix":4},"o":{"a":0,"k":100,"ix":5},"r":1,"bm":0,"nm":"Fill 1","mn":"ADBE Vector Graphic - Fill","hd":false},{"ty":"tr","p":{"a":0,"k":[228.89,791.61],"ix":2},"a":{"a":0,"k":[0,0],"ix":1},"s":{"a":0,"k":[100,100],"ix":3},"r":{"a":0,"k":0,"ix":6},"o":{"a":0,"k":100,"ix":7},"sk":{"a":0,"k":0,"ix":4},"sa":{"a":0,"k":0,"ix":5},"nm":"Transform"}],"nm":"Group 9","np":2,"cix":2,"bm":0,"ix":9,"mn":"ADBE Vector Group","hd":false},{"ty":"gr","it":[{"ind":0,"ty":"sh","ix":1,"ks":{"a":0,"k":{"i":[[42.16,0],[0,0],[0,42.08],[0,0],[-42.08,0],[0,0],[0,-42.08],[0,0]],"o":[[0,0],[-42.08,0],[0,0],[0,-42.08],[0,0],[42.08,0],[0,0],[-0.08,42.08]],"v":[[152.36,480],[-152.44,480],[-228.68,403.76],[-228.68,-403.76],[-152.44,-480],[152.44,-480],[228.68,-403.76],[228.68,403.76]],"c":true},"ix":2},"nm":"Path 1","mn":"ADBE Vector Shape - Group","hd":false},{"ty":"fl","c":{"a":0,"k":[0.258999992819,0.258999992819,0.258999992819,1],"ix":4},"o":{"a":0,"k":100,"ix":5},"r":1,"bm":0,"nm":"Fill 1","mn":"ADBE Vector Graphic - Fill","hd":false},{"ty":"tr","p":{"a":0,"k":[228.93,480.25],"ix":2},"a":{"a":0,"k":[0,0],"ix":1},"s":{"a":0,"k":[100,100],"ix":3},"r":{"a":0,"k":0,"ix":6},"o":{"a":0,"k":100,"ix":7},"sk":{"a":0,"k":0,"ix":4},"sa":{"a":0,"k":0,"ix":5},"nm":"Transform"}],"nm":"Group 10","np":2,"cix":2,"bm":0,"ix":10,"mn":"ADBE Vector Group","hd":false}],"ip":0,"op":76,"st":0,"ct":1,"bm":0}],"markers":[{"tm":0,"cm":"rest","dr":0}],"props":{}}